MANIFEST.in
README.rst
setup.py
tgext/__init__.py
tgext.langdomain.egg-info/PKG-INFO
tgext.langdomain.egg-info/SOURCES.txt
tgext.langdomain.egg-info/dependency_links.txt
tgext.langdomain.egg-info/entry_points.txt
tgext.langdomain.egg-info/namespace_packages.txt
tgext.langdomain.egg-info/not-zip-safe
tgext.langdomain.egg-info/requires.txt
tgext.langdomain.egg-info/top_level.txt
tgext/langdomain/__init__.py
tgext/langdomain/lang.py