Metadata-Version: 1.0
Name: tgext.langdomain
Version: 0.0.1
Summary: TurboGears2 extension for detecting user language from the domain
Home-page: https://bitbucket.org/axant/tgext.langdomain
Author: AXANT
Author-email: tech@axant.it
License: MIT
Keywords: turbogears2.extension
Platform: UNKNOWN
